[
  {
    "name": "Anotony Sam Roberts",
    "medical_lic_num": "DN8735",
    "address": "2200 W Cypress Creek Rd",
    "city": "Fort Lauderdale",
    "state": "Florida",
    "country": "USA",
    "pref_cont_metd": "E-Mail",
    "org_email_Addr": "antony.r@ghmc.com",
    "org_name": "Green Hill Medical Center",
    "org_website": "www.ghmc.com",
    "org_Addr": "2200 W Cypress Creek Rd",
    "org_city": "Fort Lauderdale",
    "org_State": "Florida",
    "Country": "USA",
    "insti_tax_num": "P99995952",
    "id": 1
  },
  {
    "name": "Robert James Brown",
    "medical_lic_num": "RT8735",
    "address": "37 S. Augusta St.",
    "city": "Desoto",
    "state": "Texas",
    "country": "USA",
    "pref_cont_metd": "Phone",
    "org_email_Addr": "robert.j@aj.com",
    "org_name": "James Hospital",
    "org_website": "www.jameshospitals.com",
    "org_Addr": "37 S. Augusta St.",
    "org_city": "Desoto",
    "org_State": "Texas",
    "Country": "USA",
    "insti_tax_num": "P89449537",
    "id": 2
  },
  {
    "name": "Stella Olive Conner",
    "medical_lic_num": "DN8735A",
    "address": "77 Lantern Ave.",
    "city": "Goldsboro",
    "state": "North Carolina",
    "country": "USA",
    "pref_cont_metd": "Fax",
    "org_email_Addr": "stella.o@so.com",
    "org_name": "Olive Care",
    "org_website": "www.olivecare.com",
    "org_Addr": "77 Lantern Ave.",
    "org_city": "Goldsboro",
    "org_State": "North Carolina",
    "Country": "USA",
    "insti_tax_num": "P22896178",
    "id": 3
  },
  {
    "name": "Eva Mary Martin",
    "medical_lic_num": "DN8735D",
    "address": "9715 S. Park Street",
    "city": "Mount Vernon",
    "state": "New York",
    "country": "USA",
    "pref_cont_metd": "Email",
    "org_email_Addr": "eva.m@em.com",
    "org_name": "Martin Group of Hospitals",
    "org_website": "www.martingroup.com",
    "org_Addr": "9715 S. Park Street",
    "org_city": "Mount Vernon",
    "org_State": "New York",
    "Country": "USA",
    "insti_tax_num": "P77374132",
    "id": 4
  },
  {
    "name": "Hector Raymond",
    "medical_lic_num": "DN9905",
    "address": "4651  Sardis Station",
    "city": "Golden Valley",
    "state": "Minnesota",
    "country": "USA",
    "pref_cont_metd": "FAX",
    "org_email_Addr": "hector.r@blossomvalehospitals.com",
    "org_name": "Blossomvale Hospital",
    "org_website": "www.blossomvalehospital.com",
    "org_Addr": "4651  Sardis Station",
    "org_city": "Golden Valley",
    "org_State": "Minnesota",
    "Country": "USA",
    "insti_tax_num": "P37413354",
    "id": 5
  },
  {
    "name": "Annie Williams",
    "medical_lic_num": "RT8998A",
    "address": "137 Teaticket Hwy",
    "city": "East Falmouth",
    "state": "Massachusetts",
    "country": "USA",
    "pref_cont_metd": "Email",
    "org_email_Addr": "annie.w@freemanhospital.com",
    "org_name": "Freeman Hospital Center",
    "org_website": "www.freemanhospitalcenter.com",
    "org_Addr": "137 Teaticket Hwy",
    "org_city": "East Falmouth",
    "org_State": "Massachusetts",
    "Country": "USA",
    "insti_tax_num": "P76794134",
    "id": 6
  },
  {
    "name": "Maud Hemingway",
    "medical_lic_num": "DN7891A",
    "address": "123, Genesse St,",
    "city": "Camillus",
    "state": "New York",
    "country": "USA",
    "pref_cont_metd": "Phone",
    "org_email_Addr": "Maud.h@highlandhospitals.com",
    "org_name": "Highland Hospital Center",
    "org_website": "www.highlandhospitalcenter.com",
    "org_Addr": "123, Genesse St,",
    "org_city": "Camillus",
    "org_State": "New York",
    "Country": "USA",
    "insti_tax_num": "P88374135",
    "id": 7
  },
  {
    "name": "Jessica Parker",
    "medical_lic_num": "DN5678D",
    "address": "3018 East Ave,",
    "city": "Central Square",
    "state": "New York",
    "country": "USA",
    "pref_cont_metd": "Phone",
    "org_email_Addr": "jessica.p@greenhill.com",
    "org_name": "Green Hill Medical Center",
    "org_website": "www.greenhillmedicalcenter.com",
    "org_Addr": "3018 East Ave,",
    "org_city": "Central Square",
    "org_State": "New York",
    "Country": "USA",
    "insti_tax_num": "P77374136",
    "id": 8
  }
]